README.rst
setup.py
autobahn_python_runners.egg-info/PKG-INFO
autobahn_python_runners.egg-info/SOURCES.txt
autobahn_python_runners.egg-info/dependency_links.txt
autobahn_python_runners.egg-info/entry_points.txt
autobahn_python_runners.egg-info/requires.txt
autobahn_python_runners.egg-info/top_level.txt
opendna/__init__.py
opendna/autobahn/__init__.py
opendna/autobahn/runners/__init__.py
opendna/autobahn/runners/_version.py
opendna/autobahn/runners/multirun_asyncio.py
opendna/autobahn/runners/run_asyncio.py
opendna/autobahn/runners/run_twisted.py